Metadata-Version: 2.1
Name: ango
Version: 1.3.48
Summary: Ango-Hub SDK
Author: Faruk Karakaya
Author-email: <faruk@imerit.net>
License: UNKNOWN
Keywords: imerit_ango,angohub,Ango,Ango Hub,iMerit
Platform: UNKNOWN
Classifier: Development Status :: 4 - Beta
Classifier: Programming Language :: Python :: 3
Requires-Dist: python-socketio~=5.14.3
Requires-Dist: APScheduler~=3.9.1
Requires-Dist: websocket-client
Requires-Dist: flask-socketio~=5.3.4
Requires-Dist: requests~=2.32.4
Requires-Dist: tqdm
Requires-Dist: validators~=0.20.0
Requires-Dist: boto3==1.*
Requires-Dist: fastapi~=0.120.2
Requires-Dist: uvicorn~=0.24.0
Requires-Dist: python-dotenv~=1.0.1
Requires-Dist: mangum~=0.17.0
Requires-Dist: lxml~=5.3.0
Requires-Dist: requests-toolbelt~=1.0.0
